[
  {
    "website": "https://bureauborsche.com",
    "name": "Bureau Borsche",
    "country": "DE",
    "city": "Munich",
    "tags": ["digital", "editorial", "graphic", "art-direction"],
    "author": "Moritz",
    "favorite": "Domenico"
  },
  
  {
    "website": "https://nicolastattmann.com",
    "name": "Nicola Stattmann",
    "country": "DE",
    "city": "Frankfurt",
    "tags": ["product", "furniture"],
    "author": "Moritz"
  },

  {
    "website": "https://www.duo-ade.com",    
    "name": "Duo Ade",
    "country": "DE",
    "city": "Berlin",
    "tags": ["graphic", "editorial"],
    "author": "Moritz"
  },

  {
    "website": "https://schumacher-design.de",
    "name": "Schuhmacher",
    "country": "DE",
    "city": "Berlin",
    "tags": ["branding", "interaction", "multi-location"],
    "author": "Moritz"
  },

  {
    "website": "https://schumacher-design.de",
    "name": "Schuhmacher",
    "country": "DE",
    "city": "Darmstadt",
    "tags": ["branding", "interaction", "multi-location"],
    "author": "Moritz"
  },  

  {
    "website": "https://theboysclub.berlin",
    "name": "the boys club",
    "country": "DE",
    "city": "Berlin",
    "tags": ["graphic", "illustration"],
    "author": "Moritz"
  }

]

